RegressionModelPy/__init__.py
RegressionModelPy/regression.py
RegressionModelPy-2.2.2.dist-info/METADATA
RegressionModelPy-2.2.2.dist-info/WHEEL
RegressionModelPy-2.2.2.dist-info/top_level.txt
RegressionModelPy-2.2.2.dist-info/RECORD
