Metadata-Version: 2.1
Name: RegressionModelPy
Version: 2.2.2
Summary: A simple linear regression library
Author: DocJenny
Author-email: dadoktor8@gmail.com
Classifier: Programming Language :: Python :: 3
Classifier: License :: OSI Approved :: MIT License
Classifier: Operating System :: OS Independent
Requires-Python: >=3.6
Requires-Dist: pandas
Requires-Dist: numpy
Requires-Dist: matplotlib
Requires-Dist: openpyxl
